graphreader_agentic_rag/__init__.py
graphreader_agentic_rag/agent.py
graphreader_agentic_rag/chains/__init__.py
graphreader_agentic_rag/chains/answer_reasoning.py
graphreader_agentic_rag/chains/atomic_fact_check.py
graphreader_agentic_rag/chains/chunk_check.py
graphreader_agentic_rag/chains/construction_chain.py
graphreader_agentic_rag/chains/data_models.py
graphreader_agentic_rag/chains/initial_node_selection.py
graphreader_agentic_rag/chains/neighbor_select.py
graphreader_agentic_rag/chains/neo4j_utils.py
graphreader_agentic_rag/chains/prompts.py
graphreader_agentic_rag/chains/rational_chain.py
graphreader_agentic_rag/documents.py
graphreader_agentic_rag/src/__init__.py
graphreader_agentic_rag/src/utils.py
graphreader_agentic_rag-0.1.1.dist-info/METADATA
graphreader_agentic_rag-0.1.1.dist-info/WHEEL
graphreader_agentic_rag-0.1.1.dist-info/RECORD
